email_lib/__init__.py
email_lib/email_sender.py
pyemaillib-0.1.2.dist-info/METADATA
pyemaillib-0.1.2.dist-info/WHEEL
pyemaillib-0.1.2.dist-info/top_level.txt
pyemaillib-0.1.2.dist-info/RECORD
